mo_http/__init__.py
mo_http/big_data.py
mo_http/http.py
mo_http-4.482.24007.dist-info/LICENSE
mo_http-4.482.24007.dist-info/METADATA
mo_http-4.482.24007.dist-info/WHEEL
mo_http-4.482.24007.dist-info/top_level.txt
mo_http-4.482.24007.dist-info/RECORD
